odoo/addons/account_move_tier_validation_approver/README.rst
odoo/addons/account_move_tier_validation_approver/__init__.py
odoo/addons/account_move_tier_validation_approver/__manifest__.py
odoo/addons/account_move_tier_validation_approver/i18n/account_move_tier_validation_approver.pot
odoo/addons/account_move_tier_validation_approver/i18n/es.po
odoo/addons/account_move_tier_validation_approver/i18n/es_PA.po
odoo/addons/account_move_tier_validation_approver/i18n/it.po
odoo/addons/account_move_tier_validation_approver/models/__init__.py
odoo/addons/account_move_tier_validation_approver/models/account_move.py
odoo/addons/account_move_tier_validation_approver/models/res_company.py
odoo/addons/account_move_tier_validation_approver/models/res_config_settings.py
odoo/addons/account_move_tier_validation_approver/models/res_partner.py
odoo/addons/account_move_tier_validation_approver/readme/CONFIGURE.rst
odoo/addons/account_move_tier_validation_approver/readme/CONTRIBUTORS.rst
odoo/addons/account_move_tier_validation_approver/readme/DESCRIPTION.rst
odoo/addons/account_move_tier_validation_approver/readme/USAGE.rst
odoo/addons/account_move_tier_validation_approver/static/description/icon.png
odoo/addons/account_move_tier_validation_approver/static/description/index.html
odoo/addons/account_move_tier_validation_approver/tests/__init__.py
odoo/addons/account_move_tier_validation_approver/tests/test_account_move_tier_validation_approver.py
odoo/addons/account_move_tier_validation_approver/views/account_move_views.xml
odoo/addons/account_move_tier_validation_approver/views/res_config_settings_views.xml
odoo/addons/account_move_tier_validation_approver/views/res_partner_views.xml
odoo14_addon_account_move_tier_validation_approver-14.0.1.0.1.dev9.dist-info/METADATA
odoo14_addon_account_move_tier_validation_approver-14.0.1.0.1.dev9.dist-info/WHEEL
odoo14_addon_account_move_tier_validation_approver-14.0.1.0.1.dev9.dist-info/top_level.txt
odoo14_addon_account_move_tier_validation_approver-14.0.1.0.1.dev9.dist-info/RECORD
